{"animais": [{"codigo": "002", "nome": "geruso", "especie": "pato", "ra\u00e7a": "indefinido", "idade": "5 meses", "sexo": "m", "preco": 50.0}, {"codigo": "003", "nome": "Ju", "especie": "gato", "ra\u00e7a": "vira lata", "idade": "1 ano", "sexo": "m", "preco": 0.0}], "produtos": [{"codigo": "001", "nome": "racao", "descricao": "racao para gato 1kg", "preco": 7.0}, {"codigo": "002", "nome": "Shampoo antipulgas", "descricao": "shampoo antipulgas para cachorro 400ml", "preco": 5.0}], "servicos": [{"codigo": "001", "nome": "banho", "descricao": "banho cachorro pequeno", "preco": 30.0}], "clientes": [{"codigo": "065", "nome": "Joao", "telefone": "999999999", "endereco": "rua xxx"}], "funcionarios": [{"codigo": "001", "nome": "Luis", "cargo": "caixa"}], "carrinho": {"itens": [{"codigo": "001", "nome": "racao", "descricao": "racao para gato 1kg", "preco": 7.0}], "total": 14.0}}